Saturar/__init__.py
Saturar/anotador_multimedia.py
Saturar/categorias.py
Saturar/categorizacion.py
Saturar/codificar.py
Saturar/codigos.py
Saturar/cuadernos.py
Saturar/main.py
Saturar/multimedia.py
Saturar/nueva_categoria.py
Saturar/nueva_pagina.py
Saturar/nueva_proyecto.py
Saturar/nuevo_cod.py
Saturar/nuevo_cuaderno.py
Saturar/paginas.py
Saturar/saturar.py
Saturar/utils.py
Saturar/img/buscar.png
Saturar/img/calculador.png
Saturar/img/categorias.png
Saturar/img/categorizar.png
Saturar/img/codificar.png
Saturar/img/codigos.png
Saturar/img/cuaderno.png
Saturar/img/inicial.png
Saturar/img/menu.png
Saturar/img/paginas.png
Saturar/img/reportes.png
Saturar/reportes/__init__.py
Saturar/reportes/buscador.py
Saturar/reportes/prueba_booleanos.py
Saturar/reportes/reporte_codigos.py
Saturar/reportes/reporte_nodos.py
Saturar/reportes/reporte_nube.py
Saturar/reportes/saturapi.py
Saturar/reportes/visor_reportes.py
Saturar-0.0.1.dist-info/COPYING
Saturar-0.0.1.dist-info/METADATA
Saturar-0.0.1.dist-info/WHEEL
Saturar-0.0.1.dist-info/entry_points.txt
Saturar-0.0.1.dist-info/top_level.txt
Saturar-0.0.1.dist-info/RECORD
