Metadata-Version: 2.1
Name: Saturar
Version: 0.0.1
Summary: software para analisis QDA
Home-page: http://satur.ar
Author: Valentín Basel
Author-email: valentinbasel@gmail.com
License: GPL 3.0
Platform: UNKNOWN
License-File: COPYING
Requires-Dist: numpy
Requires-Dist: pandas
Requires-Dist: pillow
Requires-Dist: wordcloud
Requires-Dist: nltk
Requires-Dist: networkx
Requires-Dist: scipy
Requires-Dist: python-vlc
Requires-Dist: stop-words
Requires-Dist: pygtkspellcheck
